{
  "daily": {
    "2025-12-18": {
      "fitness": 0,
      "english": 30,
      "research": 0,
      "reading": null
    },
    "2025-12-19": {
      "fitness": 84,
      "english": 0,
      "research": 0,
      "reading": null
    },
    "2025-12-20": {
      "fitness": 72,
      "english": 0,
      "research": 0,
      "reading": null
    }
  },
  "weekly": {
    "2025-W51": {
      "fitness": 156,
      "english": 30,
      "research": 0,
      "days": 0
    }
  },
  "monthly": {
    "2025-12": {
      "fitness": 156,
      "english": 30,
      "research": 0,
      "days": 0
    }
  },
  "yearly": {
    "2025": {
      "fitness": 156,
      "english": 30,
      "research": 0,
      "days": 3
    }
  },
  "books": []
}